{"nodes": [{"id": "c_users_azizn_onedrive_desktop_project1_backend_services_pdf_to_images_py", "label": "pdf_to_images.py", "file_type": "code", "source_file": "C:\\Users\\azizn\\OneDrive\\Desktop\\Project1\\backend\\services\\pdf_to_images.py", "source_location": "L1"}, {"id": "services_pdf_to_images_pdfconverter", "label": "PDFConverter", "file_type": "code", "source_file": "C:\\Users\\azizn\\OneDrive\\Desktop\\Project1\\backend\\services\\pdf_to_images.py", "source_location": "L16"}, {"id": "services_pdf_to_images_pdfconverter_init", "label": ".__init__()", "file_type": "code", "source_file": "C:\\Users\\azizn\\OneDrive\\Desktop\\Project1\\backend\\services\\pdf_to_images.py", "source_location": "L19"}, {"id": "services_pdf_to_images_pdfconverter_convert_from_file", "label": ".convert_from_file()", "file_type": "code", "source_file": "C:\\Users\\azizn\\OneDrive\\Desktop\\Project1\\backend\\services\\pdf_to_images.py", "source_location": "L31"}, {"id": "services_pdf_to_images_pdfconverter_convert_from_bytes", "label": ".convert_from_bytes()", "file_type": "code", "source_file": "C:\\Users\\azizn\\OneDrive\\Desktop\\Project1\\backend\\services\\pdf_to_images.py", "source_location": "L78"}, {"id": "services_pdf_to_images_pdfconverter_get_images_as_pil", "label": ".get_images_as_pil()", "file_type": "code", "source_file": "C:\\Users\\azizn\\OneDrive\\Desktop\\Project1\\backend\\services\\pdf_to_images.py", "source_location": "L125"}, {"id": "services_pdf_to_images_pdfconverter_get_page_count", "label": ".get_page_count()", "file_type": "code", "source_file": "C:\\Users\\azizn\\OneDrive\\Desktop\\Project1\\backend\\services\\pdf_to_images.py", "source_location": "L159"}, {"id": "services_pdf_to_images_get_pdf_converter", "label": "get_pdf_converter()", "file_type": "code", "source_file": "C:\\Users\\azizn\\OneDrive\\Desktop\\Project1\\backend\\services\\pdf_to_images.py", "source_location": "L180"}, {"id": "services_pdf_to_images_rationale_1", "label": "PDF to Images Conversion Service Converts PDF pages to PNG images for OCR proce", "file_type": "rationale", "source_file": "C:\\Users\\azizn\\OneDrive\\Desktop\\Project1\\backend\\services\\pdf_to_images.py", "source_location": "L1"}, {"id": "services_pdf_to_images_rationale_17", "label": "Converts PDF files to images", "file_type": "rationale", "source_file": "C:\\Users\\azizn\\OneDrive\\Desktop\\Project1\\backend\\services\\pdf_to_images.py", "source_location": "L17"}, {"id": "services_pdf_to_images_rationale_20", "label": "Initialize PDF converter                  Args:             dpi: Resolution f", "file_type": "rationale", "source_file": "C:\\Users\\azizn\\OneDrive\\Desktop\\Project1\\backend\\services\\pdf_to_images.py", "source_location": "L20"}, {"id": "services_pdf_to_images_rationale_32", "label": "Convert PDF file to images using PyMuPDF                  Args:             p", "file_type": "rationale", "source_file": "C:\\Users\\azizn\\OneDrive\\Desktop\\Project1\\backend\\services\\pdf_to_images.py", "source_location": "L32"}, {"id": "services_pdf_to_images_rationale_79", "label": "Convert PDF bytes to images using PyMuPDF          Args:             pdf_byte", "file_type": "rationale", "source_file": "C:\\Users\\azizn\\OneDrive\\Desktop\\Project1\\backend\\services\\pdf_to_images.py", "source_location": "L79"}, {"id": "services_pdf_to_images_rationale_126", "label": "Convert PDF to PIL Image objects (in-memory, no disk I/O)                  Arg", "file_type": "rationale", "source_file": "C:\\Users\\azizn\\OneDrive\\Desktop\\Project1\\backend\\services\\pdf_to_images.py", "source_location": "L126"}, {"id": "services_pdf_to_images_rationale_160", "label": "Get the number of pages in a PDF without full conversion                  Args", "file_type": "rationale", "source_file": "C:\\Users\\azizn\\OneDrive\\Desktop\\Project1\\backend\\services\\pdf_to_images.py", "source_location": "L160"}, {"id": "services_pdf_to_images_rationale_181", "label": "Factory function to create PDFConverter instance", "file_type": "rationale", "source_file": "C:\\Users\\azizn\\OneDrive\\Desktop\\Project1\\backend\\services\\pdf_to_images.py", "source_location": "L181"}], "edges": [{"source": "c_users_azizn_onedrive_desktop_project1_backend_services_pdf_to_images_py", "target": "pymupdf", "relation": "imports", "context": "import", "confidence": "EXTRACTED", "source_file": "C:\\Users\\azizn\\OneDrive\\Desktop\\Project1\\backend\\services\\pdf_to_images.py", "source_location": "L5", "weight": 1.0}, {"source": "c_users_azizn_onedrive_desktop_project1_backend_services_pdf_to_images_py", "target": "typing", "relation": "imports_from", "context": "import", "confidence": "EXTRACTED", "source_file": "C:\\Users\\azizn\\OneDrive\\Desktop\\Project1\\backend\\services\\pdf_to_images.py", "source_location": "L6", "weight": 1.0}, {"source": "c_users_azizn_onedrive_desktop_project1_backend_services_pdf_to_images_py", "target": "pil", "relation": "imports_from", "context": "import", "confidence": "EXTRACTED", "source_file": "C:\\Users\\azizn\\OneDrive\\Desktop\\Project1\\backend\\services\\pdf_to_images.py", "source_location": "L7", "weight": 1.0}, {"source": "c_users_azizn_onedrive_desktop_project1_backend_services_pdf_to_images_py", "target": "logging", "relation": "imports", "context": "import", "confidence": "EXTRACTED", "source_file": "C:\\Users\\azizn\\OneDrive\\Desktop\\Project1\\backend\\services\\pdf_to_images.py", "source_location": "L8", "weight": 1.0}, {"source": "c_users_azizn_onedrive_desktop_project1_backend_services_pdf_to_images_py", "target": "tempfile", "relation": "imports", "context": "import", "confidence": "EXTRACTED", "source_file": "C:\\Users\\azizn\\OneDrive\\Desktop\\Project1\\backend\\services\\pdf_to_images.py", "source_location": "L9", "weight": 1.0}, {"source": "c_users_azizn_onedrive_desktop_project1_backend_services_pdf_to_images_py", "target": "os", "relation": "imports", "context": "import", "confidence": "EXTRACTED", "source_file": "C:\\Users\\azizn\\OneDrive\\Desktop\\Project1\\backend\\services\\pdf_to_images.py", "source_location": "L10", "weight": 1.0}, {"source": "c_users_azizn_onedrive_desktop_project1_backend_services_pdf_to_images_py", "target": "io", "relation": "imports", "context": "import", "confidence": "EXTRACTED", "source_file": "C:\\Users\\azizn\\OneDrive\\Desktop\\Project1\\backend\\services\\pdf_to_images.py", "source_location": "L11", "weight": 1.0}, {"source": "c_users_azizn_onedrive_desktop_project1_backend_services_pdf_to_images_py", "target": "services_pdf_to_images_pdfconverter", "relation": "contains", "confidence": "EXTRACTED", "source_file": "C:\\Users\\azizn\\OneDrive\\Desktop\\Project1\\backend\\services\\pdf_to_images.py", "source_location": "L16", "weight": 1.0}, {"source": "services_pdf_to_images_pdfconverter", "target": "services_pdf_to_images_pdfconverter_init", "relation": "method", "confidence": "EXTRACTED", "source_file": "C:\\Users\\azizn\\OneDrive\\Desktop\\Project1\\backend\\services\\pdf_to_images.py", "source_location": "L19", "weight": 1.0}, {"source": "services_pdf_to_images_pdfconverter", "target": "services_pdf_to_images_pdfconverter_convert_from_file", "relation": "method", "confidence": "EXTRACTED", "source_file": "C:\\Users\\azizn\\OneDrive\\Desktop\\Project1\\backend\\services\\pdf_to_images.py", "source_location": "L31", "weight": 1.0}, {"source": "services_pdf_to_images_pdfconverter", "target": "services_pdf_to_images_pdfconverter_convert_from_bytes", "relation": "method", "confidence": "EXTRACTED", "source_file": "C:\\Users\\azizn\\OneDrive\\Desktop\\Project1\\backend\\services\\pdf_to_images.py", "source_location": "L78", "weight": 1.0}, {"source": "services_pdf_to_images_pdfconverter", "target": "services_pdf_to_images_pdfconverter_get_images_as_pil", "relation": "method", "confidence": "EXTRACTED", "source_file": "C:\\Users\\azizn\\OneDrive\\Desktop\\Project1\\backend\\services\\pdf_to_images.py", "source_location": "L125", "weight": 1.0}, {"source": "services_pdf_to_images_pdfconverter", "target": "services_pdf_to_images_pdfconverter_get_page_count", "relation": "method", "confidence": "EXTRACTED", "source_file": "C:\\Users\\azizn\\OneDrive\\Desktop\\Project1\\backend\\services\\pdf_to_images.py", "source_location": "L159", "weight": 1.0}, {"source": "c_users_azizn_onedrive_desktop_project1_backend_services_pdf_to_images_py", "target": "services_pdf_to_images_get_pdf_converter", "relation": "contains", "confidence": "EXTRACTED", "source_file": "C:\\Users\\azizn\\OneDrive\\Desktop\\Project1\\backend\\services\\pdf_to_images.py", "source_location": "L180", "weight": 1.0}, {"source": "services_pdf_to_images_get_pdf_converter", "target": "services_pdf_to_images_pdfconverter", "relation": "calls", "context": "call", "confidence": "EXTRACTED", "source_file": "C:\\Users\\azizn\\OneDrive\\Desktop\\Project1\\backend\\services\\pdf_to_images.py", "source_location": "L182", "weight": 1.0}, {"source": "services_pdf_to_images_rationale_1", "target": "c_users_azizn_onedrive_desktop_project1_backend_services_pdf_to_images_py", "relation": "rationale_for", "confidence": "EXTRACTED", "source_file": "C:\\Users\\azizn\\OneDrive\\Desktop\\Project1\\backend\\services\\pdf_to_images.py", "source_location": "L1", "weight": 1.0}, {"source": "services_pdf_to_images_rationale_17", "target": "services_pdf_to_images_pdfconverter", "relation": "rationale_for", "confidence": "EXTRACTED", "source_file": "C:\\Users\\azizn\\OneDrive\\Desktop\\Project1\\backend\\services\\pdf_to_images.py", "source_location": "L17", "weight": 1.0}, {"source": "services_pdf_to_images_rationale_20", "target": "services_pdf_to_images_pdfconverter_init", "relation": "rationale_for", "confidence": "EXTRACTED", "source_file": "C:\\Users\\azizn\\OneDrive\\Desktop\\Project1\\backend\\services\\pdf_to_images.py", "source_location": "L20", "weight": 1.0}, {"source": "services_pdf_to_images_rationale_32", "target": "services_pdf_to_images_pdfconverter_convert_from_file", "relation": "rationale_for", "confidence": "EXTRACTED", "source_file": "C:\\Users\\azizn\\OneDrive\\Desktop\\Project1\\backend\\services\\pdf_to_images.py", "source_location": "L32", "weight": 1.0}, {"source": "services_pdf_to_images_rationale_79", "target": "services_pdf_to_images_pdfconverter_convert_from_bytes", "relation": "rationale_for", "confidence": "EXTRACTED", "source_file": "C:\\Users\\azizn\\OneDrive\\Desktop\\Project1\\backend\\services\\pdf_to_images.py", "source_location": "L79", "weight": 1.0}, {"source": "services_pdf_to_images_rationale_126", "target": "services_pdf_to_images_pdfconverter_get_images_as_pil", "relation": "rationale_for", "confidence": "EXTRACTED", "source_file": "C:\\Users\\azizn\\OneDrive\\Desktop\\Project1\\backend\\services\\pdf_to_images.py", "source_location": "L126", "weight": 1.0}, {"source": "services_pdf_to_images_rationale_160", "target": "services_pdf_to_images_pdfconverter_get_page_count", "relation": "rationale_for", "confidence": "EXTRACTED", "source_file": "C:\\Users\\azizn\\OneDrive\\Desktop\\Project1\\backend\\services\\pdf_to_images.py", "source_location": "L160", "weight": 1.0}, {"source": "services_pdf_to_images_rationale_181", "target": "services_pdf_to_images_get_pdf_converter", "relation": "rationale_for", "confidence": "EXTRACTED", "source_file": "C:\\Users\\azizn\\OneDrive\\Desktop\\Project1\\backend\\services\\pdf_to_images.py", "source_location": "L181", "weight": 1.0}], "raw_calls": [{"caller_nid": "services_pdf_to_images_pdfconverter_init", "callee": "info", "is_member_call": true, "source_file": "C:\\Users\\azizn\\OneDrive\\Desktop\\Project1\\backend\\services\\pdf_to_images.py", "source_location": "L29"}, {"caller_nid": "services_pdf_to_images_pdfconverter_convert_from_file", "callee": "mkdtemp", "is_member_call": true, "source_file": "C:\\Users\\azizn\\OneDrive\\Desktop\\Project1\\backend\\services\\pdf_to_images.py", "source_location": "L45"}, {"caller_nid": "services_pdf_to_images_pdfconverter_convert_from_file", "callee": "makedirs", "is_member_call": true, "source_file": "C:\\Users\\azizn\\OneDrive\\Desktop\\Project1\\backend\\services\\pdf_to_images.py", "source_location": "L47"}, {"caller_nid": "services_pdf_to_images_pdfconverter_convert_from_file", "callee": "info", "is_member_call": true, "source_file": "C:\\Users\\azizn\\OneDrive\\Desktop\\Project1\\backend\\services\\pdf_to_images.py", "source_location": "L50"}, {"caller_nid": "services_pdf_to_images_pdfconverter_convert_from_file", "callee": "open", "is_member_call": true, "source_file": "C:\\Users\\azizn\\OneDrive\\Desktop\\Project1\\backend\\services\\pdf_to_images.py", "source_location": "L51"}, {"caller_nid": "services_pdf_to_images_pdfconverter_convert_from_file", "callee": "splitext", "is_member_call": true, "source_file": "C:\\Users\\azizn\\OneDrive\\Desktop\\Project1\\backend\\services\\pdf_to_images.py", "source_location": "L55"}, {"caller_nid": "services_pdf_to_images_pdfconverter_convert_from_file", "callee": "basename", "is_member_call": true, "source_file": "C:\\Users\\azizn\\OneDrive\\Desktop\\Project1\\backend\\services\\pdf_to_images.py", "source_location": "L55"}, {"caller_nid": "services_pdf_to_images_pdfconverter_convert_from_file", "callee": "Matrix", "is_member_call": true, "source_file": "C:\\Users\\azizn\\OneDrive\\Desktop\\Project1\\backend\\services\\pdf_to_images.py", "source_location": "L59"}, {"caller_nid": "services_pdf_to_images_pdfconverter_convert_from_file", "callee": "range", "is_member_call": false, "source_file": "C:\\Users\\azizn\\OneDrive\\Desktop\\Project1\\backend\\services\\pdf_to_images.py", "source_location": "L61"}, {"caller_nid": "services_pdf_to_images_pdfconverter_convert_from_file", "callee": "len", "is_member_call": false, "source_file": "C:\\Users\\azizn\\OneDrive\\Desktop\\Project1\\backend\\services\\pdf_to_images.py", "source_location": "L61"}, {"caller_nid": "services_pdf_to_images_pdfconverter_convert_from_file", "callee": "get_pixmap", "is_member_call": true, "source_file": "C:\\Users\\azizn\\OneDrive\\Desktop\\Project1\\backend\\services\\pdf_to_images.py", "source_location": "L63"}, {"caller_nid": "services_pdf_to_images_pdfconverter_convert_from_file", "callee": "join", "is_member_call": true, "source_file": "C:\\Users\\azizn\\OneDrive\\Desktop\\Project1\\backend\\services\\pdf_to_images.py", "source_location": "L65"}, {"caller_nid": "services_pdf_to_images_pdfconverter_convert_from_file", "callee": "lower", "is_member_call": true, "source_file": "C:\\Users\\azizn\\OneDrive\\Desktop\\Project1\\backend\\services\\pdf_to_images.py", "source_location": "L65"}, {"caller_nid": "services_pdf_to_images_pdfconverter_convert_from_file", "callee": "save", "is_member_call": true, "source_file": "C:\\Users\\azizn\\OneDrive\\Desktop\\Project1\\backend\\services\\pdf_to_images.py", "source_location": "L66"}, {"caller_nid": "services_pdf_to_images_pdfconverter_convert_from_file", "callee": "append", "is_member_call": true, "source_file": "C:\\Users\\azizn\\OneDrive\\Desktop\\Project1\\backend\\services\\pdf_to_images.py", "source_location": "L67"}, {"caller_nid": "services_pdf_to_images_pdfconverter_convert_from_file", "callee": "debug", "is_member_call": true, "source_file": "C:\\Users\\azizn\\OneDrive\\Desktop\\Project1\\backend\\services\\pdf_to_images.py", "source_location": "L68"}, {"caller_nid": "services_pdf_to_images_pdfconverter_convert_from_file", "callee": "close", "is_member_call": true, "source_file": "C:\\Users\\azizn\\OneDrive\\Desktop\\Project1\\backend\\services\\pdf_to_images.py", "source_location": "L70"}, {"caller_nid": "services_pdf_to_images_pdfconverter_convert_from_file", "callee": "info", "is_member_call": true, "source_file": "C:\\Users\\azizn\\OneDrive\\Desktop\\Project1\\backend\\services\\pdf_to_images.py", "source_location": "L71"}, {"caller_nid": "services_pdf_to_images_pdfconverter_convert_from_file", "callee": "len", "is_member_call": false, "source_file": "C:\\Users\\azizn\\OneDrive\\Desktop\\Project1\\backend\\services\\pdf_to_images.py", "source_location": "L71"}, {"caller_nid": "services_pdf_to_images_pdfconverter_convert_from_file", "callee": "error", "is_member_call": true, "source_file": "C:\\Users\\azizn\\OneDrive\\Desktop\\Project1\\backend\\services\\pdf_to_images.py", "source_location": "L75"}, {"caller_nid": "services_pdf_to_images_pdfconverter_convert_from_file", "callee": "str", "is_member_call": false, "source_file": "C:\\Users\\azizn\\OneDrive\\Desktop\\Project1\\backend\\services\\pdf_to_images.py", "source_location": "L75"}, {"caller_nid": "services_pdf_to_images_pdfconverter_convert_from_file", "callee": "Exception", "is_member_call": false, "source_file": "C:\\Users\\azizn\\OneDrive\\Desktop\\Project1\\backend\\services\\pdf_to_images.py", "source_location": "L76"}, {"caller_nid": "services_pdf_to_images_pdfconverter_convert_from_file", "callee": "str", "is_member_call": false, "source_file": "C:\\Users\\azizn\\OneDrive\\Desktop\\Project1\\backend\\services\\pdf_to_images.py", "source_location": "L76"}, {"caller_nid": "services_pdf_to_images_pdfconverter_convert_from_bytes", "callee": "mkdtemp", "is_member_call": true, "source_file": "C:\\Users\\azizn\\OneDrive\\Desktop\\Project1\\backend\\services\\pdf_to_images.py", "source_location": "L93"}, {"caller_nid": "services_pdf_to_images_pdfconverter_convert_from_bytes", "callee": "makedirs", "is_member_call": true, "source_file": "C:\\Users\\azizn\\OneDrive\\Desktop\\Project1\\backend\\services\\pdf_to_images.py", "source_location": "L95"}, {"caller_nid": "services_pdf_to_images_pdfconverter_convert_from_bytes", "callee": "info", "is_member_call": true, "source_file": "C:\\Users\\azizn\\OneDrive\\Desktop\\Project1\\backend\\services\\pdf_to_images.py", "source_location": "L98"}, {"caller_nid": "services_pdf_to_images_pdfconverter_convert_from_bytes", "callee": "open", "is_member_call": true, "source_file": "C:\\Users\\azizn\\OneDrive\\Desktop\\Project1\\backend\\services\\pdf_to_images.py", "source_location": "L99"}, {"caller_nid": "services_pdf_to_images_pdfconverter_convert_from_bytes", "callee": "Matrix", "is_member_call": true, "source_file": "C:\\Users\\azizn\\OneDrive\\Desktop\\Project1\\backend\\services\\pdf_to_images.py", "source_location": "L103"}, {"caller_nid": "services_pdf_to_images_pdfconverter_convert_from_bytes", "callee": "range", "is_member_call": false, "source_file": "C:\\Users\\azizn\\OneDrive\\Desktop\\Project1\\backend\\services\\pdf_to_images.py", "source_location": "L108"}, {"caller_nid": "services_pdf_to_images_pdfconverter_convert_from_bytes", "callee": "len", "is_member_call": false, "source_file": "C:\\Users\\azizn\\OneDrive\\Desktop\\Project1\\backend\\services\\pdf_to_images.py", "source_location": "L108"}, {"caller_nid": "services_pdf_to_images_pdfconverter_convert_from_bytes", "callee": "get_pixmap", "is_member_call": true, "source_file": "C:\\Users\\azizn\\OneDrive\\Desktop\\Project1\\backend\\services\\pdf_to_images.py", "source_location": "L110"}, {"caller_nid": "services_pdf_to_images_pdfconverter_convert_from_bytes", "callee": "join", "is_member_call": true, "source_file": "C:\\Users\\azizn\\OneDrive\\Desktop\\Project1\\backend\\services\\pdf_to_images.py", "source_location": "L112"}, {"caller_nid": "services_pdf_to_images_pdfconverter_convert_from_bytes", "callee": "lower", "is_member_call": true, "source_file": "C:\\Users\\azizn\\OneDrive\\Desktop\\Project1\\backend\\services\\pdf_to_images.py", "source_location": "L112"}, {"caller_nid": "services_pdf_to_images_pdfconverter_convert_from_bytes", "callee": "save", "is_member_call": true, "source_file": "C:\\Users\\azizn\\OneDrive\\Desktop\\Project1\\backend\\services\\pdf_to_images.py", "source_location": "L113"}, {"caller_nid": "services_pdf_to_images_pdfconverter_convert_from_bytes", "callee": "append", "is_member_call": true, "source_file": "C:\\Users\\azizn\\OneDrive\\Desktop\\Project1\\backend\\services\\pdf_to_images.py", "source_location": "L114"}, {"caller_nid": "services_pdf_to_images_pdfconverter_convert_from_bytes", "callee": "debug", "is_member_call": true, "source_file": "C:\\Users\\azizn\\OneDrive\\Desktop\\Project1\\backend\\services\\pdf_to_images.py", "source_location": "L115"}, {"caller_nid": "services_pdf_to_images_pdfconverter_convert_from_bytes", "callee": "close", "is_member_call": true, "source_file": "C:\\Users\\azizn\\OneDrive\\Desktop\\Project1\\backend\\services\\pdf_to_images.py", "source_location": "L117"}, {"caller_nid": "services_pdf_to_images_pdfconverter_convert_from_bytes", "callee": "info", "is_member_call": true, "source_file": "C:\\Users\\azizn\\OneDrive\\Desktop\\Project1\\backend\\services\\pdf_to_images.py", "source_location": "L118"}, {"caller_nid": "services_pdf_to_images_pdfconverter_convert_from_bytes", "callee": "len", "is_member_call": false, "source_file": "C:\\Users\\azizn\\OneDrive\\Desktop\\Project1\\backend\\services\\pdf_to_images.py", "source_location": "L118"}, {"caller_nid": "services_pdf_to_images_pdfconverter_convert_from_bytes", "callee": "error", "is_member_call": true, "source_file": "C:\\Users\\azizn\\OneDrive\\Desktop\\Project1\\backend\\services\\pdf_to_images.py", "source_location": "L122"}, {"caller_nid": "services_pdf_to_images_pdfconverter_convert_from_bytes", "callee": "str", "is_member_call": false, "source_file": "C:\\Users\\azizn\\OneDrive\\Desktop\\Project1\\backend\\services\\pdf_to_images.py", "source_location": "L122"}, {"caller_nid": "services_pdf_to_images_pdfconverter_convert_from_bytes", "callee": "Exception", "is_member_call": false, "source_file": "C:\\Users\\azizn\\OneDrive\\Desktop\\Project1\\backend\\services\\pdf_to_images.py", "source_location": "L123"}, {"caller_nid": "services_pdf_to_images_pdfconverter_convert_from_bytes", "callee": "str", "is_member_call": false, "source_file": "C:\\Users\\azizn\\OneDrive\\Desktop\\Project1\\backend\\services\\pdf_to_images.py", "source_location": "L123"}, {"caller_nid": "services_pdf_to_images_pdfconverter_get_images_as_pil", "callee": "info", "is_member_call": true, "source_file": "C:\\Users\\azizn\\OneDrive\\Desktop\\Project1\\backend\\services\\pdf_to_images.py", "source_location": "L136"}, {"caller_nid": "services_pdf_to_images_pdfconverter_get_images_as_pil", "callee": "open", "is_member_call": true, "source_file": "C:\\Users\\azizn\\OneDrive\\Desktop\\Project1\\backend\\services\\pdf_to_images.py", "source_location": "L137"}, {"caller_nid": "services_pdf_to_images_pdfconverter_get_images_as_pil", "callee": "Matrix", "is_member_call": true, "source_file": "C:\\Users\\azizn\\OneDrive\\Desktop\\Project1\\backend\\services\\pdf_to_images.py", "source_location": "L142"}, {"caller_nid": "services_pdf_to_images_pdfconverter_get_images_as_pil", "callee": "range", "is_member_call": false, "source_file": "C:\\Users\\azizn\\OneDrive\\Desktop\\Project1\\backend\\services\\pdf_to_images.py", "source_location": "L144"}, {"caller_nid": "services_pdf_to_images_pdfconverter_get_images_as_pil", "callee": "len", "is_member_call": false, "source_file": "C:\\Users\\azizn\\OneDrive\\Desktop\\Project1\\backend\\services\\pdf_to_images.py", "source_location": "L144"}, {"caller_nid": "services_pdf_to_images_pdfconverter_get_images_as_pil", "callee": "get_pixmap", "is_member_call": true, "source_file": "C:\\Users\\azizn\\OneDrive\\Desktop\\Project1\\backend\\services\\pdf_to_images.py", "source_location": "L146"}, {"caller_nid": "services_pdf_to_images_pdfconverter_get_images_as_pil", "callee": "tobytes", "is_member_call": true, "source_file": "C:\\Users\\azizn\\OneDrive\\Desktop\\Project1\\backend\\services\\pdf_to_images.py", "source_location": "L148"}, {"caller_nid": "services_pdf_to_images_pdfconverter_get_images_as_pil", "callee": "open", "is_member_call": true, "source_file": "C:\\Users\\azizn\\OneDrive\\Desktop\\Project1\\backend\\services\\pdf_to_images.py", "source_location": "L149"}, {"caller_nid": "services_pdf_to_images_pdfconverter_get_images_as_pil", "callee": "BytesIO", "is_member_call": true, "source_file": "C:\\Users\\azizn\\OneDrive\\Desktop\\Project1\\backend\\services\\pdf_to_images.py", "source_location": "L149"}, {"caller_nid": "services_pdf_to_images_pdfconverter_get_images_as_pil", "callee": "append", "is_member_call": true, "source_file": "C:\\Users\\azizn\\OneDrive\\Desktop\\Project1\\backend\\services\\pdf_to_images.py", "source_location": "L150"}, {"caller_nid": "services_pdf_to_images_pdfconverter_get_images_as_pil", "callee": "close", "is_member_call": true, "source_file": "C:\\Users\\azizn\\OneDrive\\Desktop\\Project1\\backend\\services\\pdf_to_images.py", "source_location": "L152"}, {"caller_nid": "services_pdf_to_images_pdfconverter_get_images_as_pil", "callee": "info", "is_member_call": true, "source_file": "C:\\Users\\azizn\\OneDrive\\Desktop\\Project1\\backend\\services\\pdf_to_images.py", "source_location": "L153"}, {"caller_nid": "services_pdf_to_images_pdfconverter_get_images_as_pil", "callee": "len", "is_member_call": false, "source_file": "C:\\Users\\azizn\\OneDrive\\Desktop\\Project1\\backend\\services\\pdf_to_images.py", "source_location": "L153"}, {"caller_nid": "services_pdf_to_images_pdfconverter_get_images_as_pil", "callee": "error", "is_member_call": true, "source_file": "C:\\Users\\azizn\\OneDrive\\Desktop\\Project1\\backend\\services\\pdf_to_images.py", "source_location": "L156"}, {"caller_nid": "services_pdf_to_images_pdfconverter_get_images_as_pil", "callee": "str", "is_member_call": false, "source_file": "C:\\Users\\azizn\\OneDrive\\Desktop\\Project1\\backend\\services\\pdf_to_images.py", "source_location": "L156"}, {"caller_nid": "services_pdf_to_images_pdfconverter_get_images_as_pil", "callee": "Exception", "is_member_call": false, "source_file": "C:\\Users\\azizn\\OneDrive\\Desktop\\Project1\\backend\\services\\pdf_to_images.py", "source_location": "L157"}, {"caller_nid": "services_pdf_to_images_pdfconverter_get_images_as_pil", "callee": "str", "is_member_call": false, "source_file": "C:\\Users\\azizn\\OneDrive\\Desktop\\Project1\\backend\\services\\pdf_to_images.py", "source_location": "L157"}, {"caller_nid": "services_pdf_to_images_pdfconverter_get_page_count", "callee": "open", "is_member_call": true, "source_file": "C:\\Users\\azizn\\OneDrive\\Desktop\\Project1\\backend\\services\\pdf_to_images.py", "source_location": "L170"}, {"caller_nid": "services_pdf_to_images_pdfconverter_get_page_count", "callee": "len", "is_member_call": false, "source_file": "C:\\Users\\azizn\\OneDrive\\Desktop\\Project1\\backend\\services\\pdf_to_images.py", "source_location": "L171"}, {"caller_nid": "services_pdf_to_images_pdfconverter_get_page_count", "callee": "close", "is_member_call": true, "source_file": "C:\\Users\\azizn\\OneDrive\\Desktop\\Project1\\backend\\services\\pdf_to_images.py", "source_location": "L172"}, {"caller_nid": "services_pdf_to_images_pdfconverter_get_page_count", "callee": "info", "is_member_call": true, "source_file": "C:\\Users\\azizn\\OneDrive\\Desktop\\Project1\\backend\\services\\pdf_to_images.py", "source_location": "L173"}, {"caller_nid": "services_pdf_to_images_pdfconverter_get_page_count", "callee": "error", "is_member_call": true, "source_file": "C:\\Users\\azizn\\OneDrive\\Desktop\\Project1\\backend\\services\\pdf_to_images.py", "source_location": "L176"}, {"caller_nid": "services_pdf_to_images_pdfconverter_get_page_count", "callee": "str", "is_member_call": false, "source_file": "C:\\Users\\azizn\\OneDrive\\Desktop\\Project1\\backend\\services\\pdf_to_images.py", "source_location": "L176"}]}